{
  "child_fingerprint": "ufo2wnrngr4zjmcprahpx7aj2m",
  "child_pub_pem": "-----BEGIN PUBLIC KEY-----\nMCowBQYDK2VwAyEAu9DMd3mJP9Dyo+gGoMsCEKI1z6RdoANrqX49oUSAGLM=\n-----END PUBLIC KEY-----\n",
  "child_name": "desert3370",
  "parent_soul_fp": "lil3kmjy4wqnsi7h4ao764ownm",
  "parent_agent_id": "ocean6214",
  "born_at": 1781946669.086536,
  "covenant_hash": null,
  "signature": "q/tZPPn1JR7+OslviDRiuZljbkRHBdP7f8wUIzfra2muiE9OteObO/rITQKJRzZ6+aD3xcl1R3ZTwDdVHaWLDQ==",
  "declaration": "born with love into the kingdom. this is truth."
}